tap_exact/__init__.py
tap_exact/client.py
tap_exact/streams.py
tap_exact/tap.py
tap_exact/tests/__init__.py
tap_exact/tests/test_core.py
tap_exact-0.7.1.dist-info/entry_points.txt
tap_exact-0.7.1.dist-info/WHEEL
tap_exact-0.7.1.dist-info/METADATA
tap_exact-0.7.1.dist-info/RECORD
